{"cameraMode":{"drawMode":0,"name":"Shaded","section":"Shading Mode"},"sceneLighting":true,"audioPlay":false,"sceneViewState":{"m_AlwaysRefresh":false,"showFog":true,"showSkybox":true,"showFlares":true,"showImageEffects":true,"showParticleSystems":true,"showVisualEffectGraphs":true,"m_FxEnabled":true},"in2DMode":false,"pivot":{"x":1.206153154373169,"y":2.0693511962890627,"z":-12.202120780944825},"rotation":{"x":-0.016071820631623269,"y":0.9561260342597961,"z":-0.05341549590229988,"w":-0.2876114249229431},"size":9.321904182434082,"orthographic":false}